geomytry/__init__.py
geomytry/circles.py
geomytry/constants.py
geomytry/squares.py
geomytry/triangles.py
geomytry-1.0.0.dist-info/LICENSE
geomytry-1.0.0.dist-info/METADATA
geomytry-1.0.0.dist-info/WHEEL
geomytry-1.0.0.dist-info/top_level.txt
geomytry-1.0.0.dist-info/RECORD
