Metadata-Version: 2.1
Name: geomytry
Version: 1.0.0
Summary: Useful functions to work with geometry
Home-page: https://github.com/mordy-python/geomytry
Author: Mordy Waldo
Author-email: imky171@gmail.com
License: MIT
Download-URL: https://pypi.org/project/geomytry/
Keywords: Geometry,Math,Shapes
Platform: UNKNOWN
Requires-Python: >=3.0.0
